Metadata-Version: 2.1
Name: configurable-shell
Version: 1.0.0
Summary: Module for building shells
Home-page: https://github.com/machinexa2/StandardShell
Author: Machine Yadav
Author-email: machinexa@gmail.com
License: MIT
Download-URL: https://github.com/machinexa2/StandardShell/archive/v1.0.0.tar.gz
Keywords: Python,Shell,RCE
Platform: UNKNOWN
Classifier: Programming Language :: Python :: 3
Classifier: License :: OSI Approved :: MIT License
Classifier: Operating System :: OS Independent
Requires-Python: >=3.8
